conversational_graph/__init__.py
conversational_graph/factory.py
conversational_graph/_internal/__init__.cpython-312-darwin.so
conversational_graph/_internal/conversation.cpython-312-darwin.so
conversational_graph/_internal/factory.cpython-312-darwin.so
conversational_graph/_internal/tools.cpython-312-darwin.so
conversational_graph/_internal/utils.cpython-312-darwin.so
conversational_graph-0.0.1.dist-info/METADATA
conversational_graph-0.0.1.dist-info/WHEEL
conversational_graph-0.0.1.dist-info/top_level.txt
conversational_graph-0.0.1.dist-info/RECORD
