Metadata-Version: 2.4
Name: conversational-graph
Version: 0.0.1
Summary: Conversational graph package
Author: Videosdk
Requires-Python: >=3.9
